Metadata-Version: 1.1
Name: bdocutils
Version: 0.0.0
Summary: Black Desert core library for private modules
Home-page: http://ntz-git.tk/IG/BDO-lib-igcore
Author: Netzulo Open Source
Author-email: netzuleando@gmail.com
License:                     GNU AFFERO GENERAL PUBLIC LICENSE
